setup.py
sambaza/Binomialdistribution.py
sambaza/Gaussiandistribution.py
sambaza/Generaldistribution.py
sambaza/__init__.py
sambaza.egg-info/PKG-INFO
sambaza.egg-info/SOURCES.txt
sambaza.egg-info/dependency_links.txt
sambaza.egg-info/not-zip-safe
sambaza.egg-info/top_level.txt